django_print_models/__init__.py
django_print_models/management/__init__.py
django_print_models/management/commands/__init__.py
django_print_models/management/commands/print_models.py
django_print_models-0.4.dist-info/LICENSE
django_print_models-0.4.dist-info/METADATA
django_print_models-0.4.dist-info/WHEEL
django_print_models-0.4.dist-info/top_level.txt
django_print_models-0.4.dist-info/RECORD
