Metadata-Version: 2.1
Name: django-print-models
Version: 0.4
Summary: A Django package to print trimmed down models for easier sharing.
Author-email: Mitchel Humpherys <mitch.special@gmail.com>
License: MIT License
Project-URL: Homepage, https://github.com/mgalgs/django_print_models
Project-URL: Bug Tracker, https://github.com/mgalgs/django_print_models/issues
Keywords: django
Classifier: Development Status :: 3 - Alpha
Classifier: Framework :: Django
Classifier: License :: OSI Approved :: MIT License
Classifier: Programming Language :: Python :: 3
Classifier: Programming Language :: Python :: 3.7
Classifier: Programming Language :: Python :: 3.8
Classifier: Programming Language :: Python :: 3.9
Requires-Python: >=3
License-File: LICENSE
Requires-Dist: django >=3.0
